Workbook

Sheet TODAY'S MOVE
B2: LeVrage ────▲─────
B4: TODAY'S MOVE
B5: =IF(COUNTA(ENGINE!A5:A14)=0,"→ Enter account data on the ENGINE tab",IF(ENGINE!B21="","No feasible move with current cash — increase cash on ENGINE tab","PAY $"&TEXT(ENGINE!B22,"#,##0")&" → "&ENGINE!B21)) -> → Enter account data on the ENGINE tab
B6: IMPACT DETAIL
B7: Account | C7: =IFERROR(ENGINE!B21,"")
B8: Current Utilization | C8: =IFERROR(ENGINE!B23,"")
B9: After This Payment | C9: =IFERROR(ENGINE!B24,"")
B11: PORTFOLIO SNAPSHOT
B12: Total Revolving Utilization | C12: =IFERROR(SUMPRODUCT((ENGINE!B5:B14<>"")*ENGINE!B5:B14)/SUMPRODUCT((ENGINE!C5:C14<>"")*ENGINE!C5:C14),"")
B13: Accounts Above 50% Utilization | C13: =COUNTIF(ENGINE!D5:D14,">0.5") -> 0
B14: Cash Available | C14: =ENGINE!B2 -> 500
B16: DATA CONFIDENCE
B17: =IF(COUNTA(ENGINE!A5:A14)=0,"No data entered — go to ENGINE tab","Data for "&COUNTA(ENGINE!A5:A14)&" account(s). Check DISCOVERY tab for unknown factors before acting on this output.") -> No data entered — go to ENGINE tab
B18: LeVrage output is based only on data provided. Unknown derogatories, reporting errors, collection accounts, or payment timing issues not entered above may affect actual score movement. The more complete your input, the more accurate the output.

Sheet ENGINE
A1: LeVrage ────▲───── DECISION ENGINE v1
A2: Cash Available to Deploy | B2: 500 | C2: ← Change this to your actual available cash before reading the output
A4: Account Name | B4: Balance | C4: Credit Limit | D4: Utilization % | E4: Target % | F4: Paydown Needed | G4: Priority Score | H4: Cash Feasible | I4: Priority Rank
D5: =IF(AND(B5<>"",C5<>"",C5>0),B5/C5,"") | E5: =IF(D5="","",IF(D5>0.5,0.49,IF(D5>0.3,0.29,IF(D5>0.09,0.09,D5)))) | F5: =IF(D5="","",MAX(0,B5-(C5*E5))) | G5: =IF(D5="","",IF(F5=0,0,D5*F5)) | H5: =IF(F5="","",IF(F5=0,"—",IF(F5<=$B$2,"✓","✗"))) | I5: =IF(G5="","",IF(G5=0,"—",RANK(G5,G$5:G$14,0)))
D6: =IF(AND(B6<>"",C6<>"",C6>0),B6/C6,"") | E6: =IF(D6="","",IF(D6>0.5,0.49,IF(D6>0.3,0.29,IF(D6>0.09,0.09,D6)))) | F6: =IF(D6="","",MAX(0,B6-(C6*E6))) | G6: =IF(D6="","",IF(F6=0,0,D6*F6)) | H6: =IF(F6="","",IF(F6=0,"—",IF(F6<=$B$2,"✓","✗"))) | I6: =IF(G6="","",IF(G6=0,"—",RANK(G6,G$5:G$14,0)))
D7: =IF(AND(B7<>"",C7<>"",C7>0),B7/C7,"") | E7: =IF(D7="","",IF(D7>0.5,0.49,IF(D7>0.3,0.29,IF(D7>0.09,0.09,D7)))) | F7: =IF(D7="","",MAX(0,B7-(C7*E7))) | G7: =IF(D7="","",IF(F7=0,0,D7*F7)) | H7: =IF(F7="","",IF(F7=0,"—",IF(F7<=$B$2,"✓","✗"))) | I7: =IF(G7="","",IF(G7=0,"—",RANK(G7,G$5:G$14,0)))
D8: =IF(AND(B8<>"",C8<>"",C8>0),B8/C8,"") | E8: =IF(D8="","",IF(D8>0.5,0.49,IF(D8>0.3,0.29,IF(D8>0.09,0.09,D8)))) | F8: =IF(D8="","",MAX(0,B8-(C8*E8))) | G8: =IF(D8="","",IF(F8=0,0,D8*F8)) | H8: =IF(F8="","",IF(F8=0,"—",IF(F8<=$B$2,"✓","✗"))) | I8: =IF(G8="","",IF(G8=0,"—",RANK(G8,G$5:G$14,0)))
D9: =IF(AND(B9<>"",C9<>"",C9>0),B9/C9,"") | E9: =IF(D9="","",IF(D9>0.5,0.49,IF(D9>0.3,0.29,IF(D9>0.09,0.09,D9)))) | F9: =IF(D9="","",MAX(0,B9-(C9*E9))) | G9: =IF(D9="","",IF(F9=0,0,D9*F9)) | H9: =IF(F9="","",IF(F9=0,"—",IF(F9<=$B$2,"✓","✗"))) | I9: =IF(G9="","",IF(G9=0,"—",RANK(G9,G$5:G$14,0)))
D10: =IF(AND(B10<>"",C10<>"",C10>0),B10/C10,"") | E10: =IF(D10="","",IF(D10>0.5,0.49,IF(D10>0.3,0.29,IF(D10>0.09,0.09,D10)))) | F10: =IF(D10="","",MAX(0,B10-(C10*E10))) | G10: =IF(D10="","",IF(F10=0,0,D10*F10)) | H10: =IF(F10="","",IF(F10=0,"—",IF(F10<=$B$2,"✓","✗"))) | I10: =IF(G10="","",IF(G10=0,"—",RANK(G10,G$5:G$14,0)))
D11: =IF(AND(B11<>"",C11<>"",C11>0),B11/C11,"") | E11: =IF(D11="","",IF(D11>0.5,0.49,IF(D11>0.3,0.29,IF(D11>0.09,0.09,D11)))) | F11: =IF(D11="","",MAX(0,B11-(C11*E11))) | G11: =IF(D11="","",IF(F11=0,0,D11*F11)) | H11: =IF(F11="","",IF(F11=0,"—",IF(F11<=$B$2,"✓","✗"))) | I11: =IF(G11="","",IF(G11=0,"—",RANK(G11,G$5:G$14,0)))
D12: =IF(AND(B12<>"",C12<>"",C12>0),B12/C12,"") | E12: =IF(D12="","",IF(D12>0.5,0.49,IF(D12>0.3,0.29,IF(D12>0.09,0.09,D12)))) | F12: =IF(D12="","",MAX(0,B12-(C12*E12))) | G12: =IF(D12="","",IF(F12=0,0,D12*F12)) | H12: =IF(F12="","",IF(F12=0,"—",IF(F12<=$B$2,"✓","✗"))) | I12: =IF(G12="","",IF(G12=0,"—",RANK(G12,G$5:G$14,0)))
D13: =IF(AND(B13<>"",C13<>"",C13>0),B13/C13,"") | E13: =IF(D13="","",IF(D13>0.5,0.49,IF(D13>0.3,0.29,IF(D13>0.09,0.09,D13)))) | F13: =IF(D13="","",MAX(0,B13-(C13*E13))) | G13: =IF(D13="","",IF(F13=0,0,D13*F13)) | H13: =IF(F13="","",IF(F13=0,"—",IF(F13<=$B$2,"✓","✗"))) | I13: =IF(G13="","",IF(G13=0,"—",RANK(G13,G$5:G$14,0)))
D14: =IF(AND(B14<>"",C14<>"",C14>0),B14/C14,"") | E14: =IF(D14="","",IF(D14>0.5,0.49,IF(D14>0.3,0.29,IF(D14>0.09,0.09,D14)))) | F14: =IF(D14="","",MAX(0,B14-(C14*E14))) | G14: =IF(D14="","",IF(F14=0,0,D14*F14)) | H14: =IF(F14="","",IF(F14=0,"—",IF(F14<=$B$2,"✓","✗"))) | I14: =IF(G14="","",IF(G14=0,"—",RANK(G14,G$5:G$14,0)))
A16: BLUE = your inputs | BLACK = calculated | ✓ = paydown fits available cash | ✗ = need more cash | — = account already optimized
A17: Target thresholds: >50% util → target 49% | >30% util → target 29% | >9% util → target 9% | Priority Score = utilization × paydown needed
A18: ⚠ Recommendations are based only on data entered above. Unknown factors — collections, reporting errors, disputed items, accounts not included, or payment timing — not visible in manual input may change or delay actual score movement. Complete the DISCOVERY tab before acting on this output.
A20: RECOMMENDED ACTION (referenced by TODAY'S MOVE tab)
A21: Account Name | B21: =IFERROR(INDEX(A5:A14,MATCH(minifs(I5:I14,H5:H14,"✓"),I5:I14,0)),"")
A22: Paydown Amount | B22: =IFERROR(INDEX(F5:F14,MATCH(minifs(I5:I14,H5:H14,"✓"),I5:I14,0)),"")
A23: Current Util % | B23: =IFERROR(INDEX(D5:D14,MATCH(minifs(I5:I14,H5:H14,"✓"),I5:I14,0)),"")
A24: Target Util % | B24: =IFERROR(INDEX(E5:E14,MATCH(minifs(I5:I14,H5:H14,"✓"),I5:I14,0)),"")

Sheet DISCOVERY
B1: LeVrage ────▲───── DISCOVERY ENGINE
B3: Complete this before running the ENGINE. In mortgage, the most thorough intake is always the fastest close — because nothing surfaces at the wrong time. Same rule applies here: unknown factors that show up after the recommendation invalidate the output and cost you time. More complete input = higher confidence output.
B4: SECTION 1 — KNOWN UNKNOWNS (Factors That Can Override or Delay the Engine)
B5: Question | C5: Your Answer (overwrite) | D5: Why It Matters
B6: Do you have any accounts in collections? | C6: Yes / No / Not Sure | D6: Collections suppress your score regardless of utilization improvements. Must be addressed separately — utilization optimization alone won't overcome an active collection.
B7: Any late payments in the last 12 months? | C7: Yes / No / Not Sure | D7: Recent lates are the #1 score suppressor. The engine cannot fix a reported 30-day late — it must age out (12–24 months) or be successfully disputed.
B8: Any disputed items on your credit report? | C8: Yes / No / Not Sure | D8: Active disputes freeze the account's scoring impact. Resolve disputes before optimizing utilization around those accounts.
B9: Any charge-offs or settled accounts? | C9: Yes / No / Not Sure | D9: Long-term score weight. Cannot be fixed by utilization reduction alone. Flag for v2 dispute/resolution module.
B10: Any accounts you don't recognize on your report? | C10: Yes / No / Not Sure | D10: Possible reporting error or identity issue. FCRA Section 611 dispute — creditor has 30 days to verify or it must be removed.
B11: Do you know your statement closing dates for each card? | C11: Yes / No / Not Sure | D11: Statement closing date (not due date) is when your balance gets reported to the bureaus. Paying before closing date changes the reported number. This becomes v2 — Timing Intelligence Engine.
B12: Any authorized user accounts on your report? | C12: Yes / No / Not Sure | D12: Authorized user accounts still count toward your utilization score. Include all of them on the ENGINE tab, even if the card belongs to someone else.
B13: Any accounts opened in the last 6 months? | C13: Yes / No / Not Sure | D13: New accounts lower your average account age. Not an immediate blocker for utilization optimization, but factors into long-term sequencing.
B14: Do you know which bureau your target lender pulls? | C14: Yes / No / Not Sure | D14: Mortgage lenders use FICO 2/4/5. Most card issuers use FICO 8. The score you see on your bank app is likely not the same score a lender sees. (v2 feature: lender-specific score mapping.)
B16: SECTION 2 — ACCOUNT INVENTORY (What to Include on the ENGINE Tab)
B17: Account Type | C17: Include in ENGINE? | D17: Notes
B18: Credit cards (revolving) | C18: YES — always | D18: Core input. Include every revolving account.
B19: Store cards (revolving) | C19: YES — if active | D19: Often overlooked, often high utilization.
B20: Charge cards (no preset limit) | C20: YES — include balance + credit line | D20: Include if you know the limit — some bureaus report a limit.
B21: Personal loans (installment) | C21: No — v1 only | D21: Installment debt doesn't affect revolving utilization. v2 module.
B22: Auto loans | C22: No — v1 only | D22: Same — not a revolving utilization factor for v1.
B23: Mortgage | C23: No — v1 only | D23: Separate debt category. Not in revolving util calculation.
B24: Authorized user accounts | C24: YES — if on your report | D24: Count toward YOUR utilization score even if it's not your card.
B25: Collections / charge-offs | C25: No — flag in Section 1 above | D25: Not an ENGINE input. Requires separate dispute/resolution path.
B27: LeVrage v1 focuses on revolving utilization — the fastest lever available without new income or new accounts. Unknown derogatories, timing optimization, installment debt velocity, and lender-specific score mapping are v2 modules. Output quality scales directly with data completeness.
